LICENSE.txt
MANIFEST.in
README.txt
setup.py
pyvcs/__init__.py
pyvcs/commit.py
pyvcs/exceptions.py
pyvcs/repository.py
pyvcs/utils.py
pyvcs.egg-info/PKG-INFO
pyvcs.egg-info/SOURCES.txt
pyvcs.egg-info/dependency_links.txt
pyvcs.egg-info/top_level.txt
pyvcs/backends/__init__.py
pyvcs/backends/bzr.py
pyvcs/backends/git.py
pyvcs/backends/hg.py
pyvcs/backends/subversion.py