Metadata-Version: 1.0
Name: pyvcs
Version: 0.1
Summary: A lightweight abstraction layer over multiple VCSs.
Home-page: http://github.com/alex/pyvcs/
Author: Alex Gaynor, Justin Lilly
Author-email: alex.gaynor@gmail.com
License: UNKNOWN
Platform: UNKNOWN
Classifier: Development Status :: 4 - Beta
Classifier: Intended Audience :: Developers
Classifier: License :: OSI Approved :: BSD License
Classifier: Programming Language :: Python
Classifier: Topic :: Software Development :: Version Control
